pyforum/__init__.py
pyforum/pyforum.py
pyforum-0.0.1.dist-info/METADATA
pyforum-0.0.1.dist-info/WHEEL
pyforum-0.0.1.dist-info/top_level.txt
pyforum-0.0.1.dist-info/RECORD
